LICENSE
MANIFEST.in
README.md
setup.cfg
setup.py
lol/__init__.py
lol/lol.py
lolP.egg-info/PKG-INFO
lolP.egg-info/SOURCES.txt
lolP.egg-info/dependency_links.txt
lolP.egg-info/requires.txt
lolP.egg-info/top_level.txt